dcryptit/__init__.py
dcryptit/dcryptit.py
dcryptit/exceptions.py
dcryptit-2.0.dist-info/LICENSE.txt
dcryptit-2.0.dist-info/METADATA
dcryptit-2.0.dist-info/WHEEL
dcryptit-2.0.dist-info/top_level.txt
dcryptit-2.0.dist-info/RECORD
