Metadata-Version: 2.1
Name: dcryptit
Version: 2.0
Summary: A library for interacting with dcrypt.it
Home-page: https://github.com/ianling/dcryptit-python
Author: Ian Ling
Author-email: ian@iancaling.com
License: UNKNOWN
Download-URL: https://github.com/ianling/dcryptit-python/archive/2.0.tar.gz
Keywords: parse,dlc,decryptit,decrypt,dcrypt
Platform: UNKNOWN
Requires-Dist: requests
